Workbook
Name dropdown: Refs!$A$2:$A$6
Name mat: Refs!#REF!
Name score: Refs!$A$1:$A$7

Sheet Cover Page
C3: Sustainable Business Self Assessment
B4: Version 2. May 2025
B6: Copyright © 2025 Sustainable Business Alliance. All rights reserved. VAT Number: GB482165582. Registered Company Number: 14752074

Sheet Instructions
B2: Sustainable Business Self Assessment
B3: Instructions
B4: Welcome to the SBA Sustainable Business Self Assessment This simple tool is designed to help you reflect on your current sustainability practices and identify areas where your business can improve. By completing the Scorecard, you’ll get a clear, high-level picture of how well you are managing key environmental, social, and governance (ESG) topics. The results can help you prioritise actions, communicate progress to stakeholders, or start conversations within your business about how to embed sustainability.
B5: How long will it take? The Self Assessment is designed to be quick and easy to complete. It should take around 5-10 minutes, depending on how familiar you are with your business’s sustainability practices. What do you need to do? 1. Go to the Scorecard tab. Read each question carefully and select the most appropriate answer from the dropdown options provided. Try to answer honestly based on what your business is currently doing, not what you plan to do in the future. 2. Review your results. After you’ve answered all the questions, go to the Report tab. Here, you will see your total score and a simple analysis of your results, highlighting your strengths and areas for improvement.
B6: Why is this important? Understanding your sustainability performance is the first step towards making meaningful improvements. This Self Assessment has been created to help small and medium-sized businesses like yours take stock of where you are today — without the jargon or complexity of formal ESG frameworks. Your results are for your own use and will not be shared without your permission.
B8: Please go to the Self Assessment and complete the questions by selecting the appropriate options from the dropdown menus.

Sheet Scores
B2: Financial Materiality
B4: Topic | C4: Operational Costs | D4: Liability Risks | E4: Score | F4: Ranking | G4: Normalised Ranking
B5: Fraud and Corruption | C5: =#REF! -> #REF! | D5: =#REF! -> #REF! | E5: =C5+D5 -> #REF! | F5: =RANK(E5,$E$5:$E$20,0) -> #REF! | G5: =10-((F5-MIN($F$5:$F$20))/(MAX($F$5:$F$20)-MIN($F$5:$F$20)))*9 -> #REF!
B6: Data Privacy | C6: =#REF! -> #REF! | D6: =#REF! -> #REF! | E6: =C6+D6 -> #REF! | F6: =RANK(E6,$E$5:$E$20,0) -> #REF! | G6: =10-((F6-MIN($F$5:$F$20))/(MAX($F$5:$F$20)-MIN($F$5:$F$20)))*9 -> #REF!
B7: Modern Slavery | C7: =#REF! -> #REF! | D7: =#REF! -> #REF! | E7: =C7+D7 -> #REF! | F7: =RANK(E7,$E$5:$E$20,0) -> #REF! | G7: =10-((F7-MIN($F$5:$F$20))/(MAX($F$5:$F$20)-MIN($F$5:$F$20)))*9 -> #REF!
B8: Labour Practices | C8: =#REF! -> #REF! | D8: =#REF! -> #REF! | E8: =C8+D8 -> #REF! | F8: =RANK(E8,$E$5:$E$20,0) -> #REF! | G8: =10-((F8-MIN($F$5:$F$20))/(MAX($F$5:$F$20)-MIN($F$5:$F$20)))*9 -> #REF!
B9: Employee Representation | C9: =#REF! -> #REF! | D9: =#REF! -> #REF! | E9: =C9+D9 -> #REF! | F9: =RANK(E9,$E$5:$E$20,0) -> #REF! | G9: =10-((F9-MIN($F$5:$F$20))/(MAX($F$5:$F$20)-MIN($F$5:$F$20)))*9 -> #REF! | K9: `
B10: Training and Development | C10: =#REF! -> #REF! | D10: =#REF! -> #REF! | E10: =C10+D10 -> #REF! | F10: =RANK(E10,$E$5:$E$20,0) -> #REF! | G10: =10-((F10-MIN($F$5:$F$20))/(MAX($F$5:$F$20)-MIN($F$5:$F$20)))*9 -> #REF!
B11: Fair Compensation | C11: =#REF! -> #REF! | D11: =#REF! -> #REF! | E11: =C11+D11 -> #REF! | F11: =RANK(E11,$E$5:$E$20,0) -> #REF! | G11: =10-((F11-MIN($F$5:$F$20))/(MAX($F$5:$F$20)-MIN($F$5:$F$20)))*9 -> #REF!
B12: Health and Wellbeing | C12: =#REF! -> #REF! | D12: =#REF! -> #REF! | E12: =C12+D12 -> #REF! | F12: =RANK(E12,$E$5:$E$20,0) -> #REF! | G12: =10-((F12-MIN($F$5:$F$20))/(MAX($F$5:$F$20)-MIN($F$5:$F$20)))*9 -> #REF!
B13: Diversity and Equality | C13: =#REF! -> #REF! | D13: =#REF! -> #REF! | E13: =C13+D13 -> #REF! | F13: =RANK(E13,$E$5:$E$20,0) -> #REF! | G13: =10-((F13-MIN($F$5:$F$20))/(MAX($F$5:$F$20)-MIN($F$5:$F$20)))*9 -> #REF!
B14: Local Communities | C14: =#REF! -> #REF! | D14: =#REF! -> #REF! | E14: =C14+D14 -> #REF! | F14: =RANK(E14,$E$5:$E$20,0) -> #REF! | G14: =10-((F14-MIN($F$5:$F$20))/(MAX($F$5:$F$20)-MIN($F$5:$F$20)))*9 -> #REF!
B15: Energy | C15: =#REF! -> #REF! | D15: =#REF! -> #REF! | E15: =C15+D15 -> #REF! | F15: =RANK(E15,$E$5:$E$20,0) -> #REF! | G15: =10-((F15-MIN($F$5:$F$20))/(MAX($F$5:$F$20)-MIN($F$5:$F$20)))*9 -> #REF!
B16: Emissions | C16: =#REF! -> #REF! | D16: =#REF! -> #REF! | E16: =C16+D16 -> #REF! | F16: =RANK(E16,$E$5:$E$20,0) -> #REF! | G16: =10-((F16-MIN($F$5:$F$20))/(MAX($F$5:$F$20)-MIN($F$5:$F$20)))*9 -> #REF!
B17: Water and Effluents | C17: =#REF! -> #REF! | D17: =#REF! -> #REF! | E17: =C17+D17 -> #REF! | F17: =RANK(E17,$E$5:$E$20,0) -> #REF! | G17: =10-((F17-MIN($F$5:$F$20))/(MAX($F$5:$F$20)-MIN($F$5:$F$20)))*9 -> #REF!
B18: Waste | C18: =#REF! -> #REF! | D18: =#REF! -> #REF! | E18: =C18+D18 -> #REF! | F18: =RANK(E18,$E$5:$E$20,0) -> #REF! | G18: =10-((F18-MIN($F$5:$F$20))/(MAX($F$5:$F$20)-MIN($F$5:$F$20)))*9 -> #REF!
B19: Materials | C19: =#REF! -> #REF! | D19: =#REF! -> #REF! | E19: =C19+D19 -> #REF! | F19: =RANK(E19,$E$5:$E$20,0) -> #REF! | G19: =10-((F19-MIN($F$5:$F$20))/(MAX($F$5:$F$20)-MIN($F$5:$F$20)))*9 -> #REF!
B20: Biodiversity | C20: =#REF! -> #REF! | D20: =#REF! -> #REF! | E20: =C20+D20 -> #REF! | F20: =RANK(E20,$E$5:$E$20,0) -> #REF! | G20: =10-((F20-MIN($F$5:$F$20))/(MAX($F$5:$F$20)-MIN($F$5:$F$20)))*9 -> #REF!
B22: Impact Materiality
B24: Topic | C24: Operational Impacts | D24: Supply Chain Impacts | E24: Score | F24: Ranking | G24: Normalised Ranking
B25: Fraud and Corruption | C25: =#REF! -> #REF! | D25: =#REF! -> #REF! | E25: =C25+D25 -> #REF! | F25: =RANK(E25,$E$25:$E$40,0) -> #REF! | G25: =10-((F25-MIN($F$25:$F$40))/(MAX($F$25:$F$40)-MIN($F$25:$F$40)))*9 -> #REF!
B26: Data Privacy | C26: =#REF! -> #REF! | D26: =#REF! -> #REF! | E26: =C26+D26 -> #REF! | F26: =RANK(E26,$E$25:$E$40,0) -> #REF! | G26: =10-((F26-MIN($F$25:$F$40))/(MAX($F$25:$F$40)-MIN($F$25:$F$40)))*9 -> #REF!
B27: Modern Slavery | C27: =#REF! -> #REF! | D27: =#REF! -> #REF! | E27: =C27+D27 -> #REF! | F27: =RANK(E27,$E$25:$E$40,0) -> #REF! | G27: =10-((F27-MIN($F$25:$F$40))/(MAX($F$25:$F$40)-MIN($F$25:$F$40)))*9 -> #REF!
B28: Labour Practices | C28: =#REF! -> #REF! | D28: =#REF! -> #REF! | E28: =C28+D28 -> #REF! | F28: =RANK(E28,$E$25:$E$40,0) -> #REF! | G28: =10-((F28-MIN($F$25:$F$40))/(MAX($F$25:$F$40)-MIN($F$25:$F$40)))*9 -> #REF!
B29: Employee Representation | C29: =#REF! -> #REF! | D29: =#REF! -> #REF! | E29: =C29+D29 -> #REF! | F29: =RANK(E29,$E$25:$E$40,0) -> #REF! | G29: =10-((F29-MIN($F$25:$F$40))/(MAX($F$25:$F$40)-MIN($F$25:$F$40)))*9 -> #REF!
B30: Training and Development | C30: =#REF! -> #REF! | D30: =#REF! -> #REF! | E30: =C30+D30 -> #REF! | F30: =RANK(E30,$E$25:$E$40,0) -> #REF! | G30: =10-((F30-MIN($F$25:$F$40))/(MAX($F$25:$F$40)-MIN($F$25:$F$40)))*9 -> #REF!
B31: Fair Compensation | C31: =#REF! -> #REF! | D31: =#REF! -> #REF! | E31: =C31+D31 -> #REF! | F31: =RANK(E31,$E$25:$E$40,0) -> #REF! | G31: =10-((F31-MIN($F$25:$F$40))/(MAX($F$25:$F$40)-MIN($F$25:$F$40)))*9 -> #REF!
B32: Health and Wellbeing | C32: =#REF! -> #REF! | D32: =#REF! -> #REF! | E32: =C32+D32 -> #REF! | F32: =RANK(E32,$E$25:$E$40,0) -> #REF! | G32: =10-((F32-MIN($F$25:$F$40))/(MAX($F$25:$F$40)-MIN($F$25:$F$40)))*9 -> #REF!
B33: Diversity and Equality | C33: =#REF! -> #REF! | D33: =#REF! -> #REF! | E33: =C33+D33 -> #REF! | F33: =RANK(E33,$E$25:$E$40,0) -> #REF! | G33: =10-((F33-MIN($F$25:$F$40))/(MAX($F$25:$F$40)-MIN($F$25:$F$40)))*9 -> #REF!
B34: Local Communities | C34: =#REF! -> #REF! | D34: =#REF! -> #REF! | E34: =C34+D34 -> #REF! | F34: =RANK(E34,$E$25:$E$40,0) -> #REF! | G34: =10-((F34-MIN($F$25:$F$40))/(MAX($F$25:$F$40)-MIN($F$25:$F$40)))*9 -> #REF!
B35: Energy | C35: =#REF! -> #REF! | D35: =#REF! -> #REF! | E35: =C35+D35 -> #REF! | F35: =RANK(E35,$E$25:$E$40,0) -> #REF! | G35: =10-((F35-MIN($F$25:$F$40))/(MAX($F$25:$F$40)-MIN($F$25:$F$40)))*9 -> #REF!
B36: Emissions | C36: =#REF! -> #REF! | D36: =#REF! -> #REF! | E36: =C36+D36 -> #REF! | F36: =RANK(E36,$E$25:$E$40,0) -> #REF! | G36: =10-((F36-MIN($F$25:$F$40))/(MAX($F$25:$F$40)-MIN($F$25:$F$40)))*9 -> #REF!
... B40: Biodiversity | C40: =#REF! -> #REF! | D40: =#REF! -> #REF! | E40: =C40+D40 -> #REF! | F40: =RANK(E40,$E$25:$E$40,0) -> #REF! | G40: =10-((F40-MIN($F$25:$F$40))/(MAX($F$25:$F$40)-MIN($F$25:$F$40)))*9 -> #REF!

Sheet Self Assessment
B2: Sustainable Business Self Assessment
B3: Please complete the Self Assessment by answering the relevant questions.
B5: General Information
B6: Please enter the name of the organisation | D6: Example Company
B8: Governance Dimension
B9: Topic | C9: Question | D9: Response | E9: Reporting Disclosures
B10: Strategic Alignment | C10: Has your company identified its key social, environmental, and governance (ESG) priorities through a structured assessment (e.g., materiality assessment) and aligned them with its mission and business strategy? | D10: Please Select | E10: ▪ Information on the company's mission and alignment to ESG priorities ▪ Matereriality Assessment report including a list of material ESG topics | G10: =VLOOKUP(D10,Refs!$A$1:$B$7,2,FALSE) -> N/A | H10: =IF(ISERROR(G10/4),"N/A",G10/"4") -> N/A
B11: Integrated Planning | C11: Have you set measurable targets for each priority and developed action plans to achieve them, embedding responsibilities into job roles and performance objectives, with necessary training provided? | D11: Please Select | E11: ▪ Information on targets set againt highest priority ESG topics ▪ Information on key actions and initiatives taken to achieve targets ▪ Approach to defining roles, responsibilities, and accountability. | G11: =VLOOKUP(D11,Refs!$A$1:$B$7,2,FALSE) -> N/A | H11: =IF(ISERROR(G11/4),"N/A",G11/"4") -> N/A
B12: Reporting and Transparency | C12: Do you publicly report on your organisation’s social and environmental impact, including progress toward targets, and has the data been independently verified? | D12: Please Select | E12: ▪ Information on where to find details on social and environmental performance ▪ Evidence of third-party verification (e.g. Limited or Reasonable Assurance Report) | G12: =VLOOKUP(D12,Refs!$A$1:$B$7,2,FALSE) -> N/A | H12: =IF(ISERROR(G12/4),"N/A",G12/"4") -> N/A
B13: Procurement | C13: Do you assess social and environmental impacts of key suppliers, set expectations for responsible practices, and engage them to drive improvements? | D13: Please Select | E13: ▪ Percentage of significant suppliers evaluated for social and environmental impacts. ▪ Information on how suppliers are engaged to improve social and environmental performance ▪ Information on on social and environmental requirements for key suppliers | G13: =VLOOKUP(D13,Refs!$A$1:$B$7,2,FALSE) -> N/A | H13: =IF(ISERROR(G13/4),"N/A",G13/"4") -> N/A
B14: Fraud and Corruption | C14: Are mechanisms in place for continuous monitoring and reporting of risks and compliance related to fraud and corruption? | D14: Please Select | E14: ▪ Information on risks related to fraud and corruption. ▪ Total number and nature of confirmed incidents of corruption. | G14: =VLOOKUP(D14,Refs!$A$1:$B$7,2,FALSE) -> N/A | H14: =IF(ISERROR(G14/4),"N/A",G14/"4") -> N/A
B15: Data Privacy | C15: Are mechanisms in place to ensure the fundamental rights to privacy and data protection of all its stakeholders when processing personal data? | D15: Please Select | E15: ▪ Information on measures taken to protect data and privacy. ▪ Number of substantiated complaints received concerning breaches of privacy of stakeholders | G15: =VLOOKUP(D15,Refs!$A$1:$B$7,2,FALSE) -> N/A | H15: =IF(ISERROR(G15/4),"N/A",G15/"4") -> N/A
B16: Modern Slavery | C16: Have you assessed and taken steps to identify and mitigate modern slavery risks in your supply chain? | D16: Please Select | E16: ▪ Operations at significant risk for incidents of child labour, forced labour and human trafficking ▪ Information on actions taken to mitigate the risk of modern slavery within the supply chain | G16: =VLOOKUP(D16,Refs!$A$1:$B$7,2,FALSE) -> N/A | H16: =IF(ISERROR(G16/4),"N/A",G16/"4") -> N/A
B17: Governance Score | D17: =IF(COUNTIF(G10:G16,"<>N/A")=0,"Awaiting Score",SUM(G10:G16)/(COUNTIF(G10:G16,"<>N/A")*4)) -> Awaiting Score
B19: Social Dimension
B20: Topic | C20: Question | D20: Response | E20: Reporting Disclosures
B21: Labour Practices | C21: Do you have policies and practices in place to ensure fair and stable employment conditions, including full-time and contract work, employee turnover management, and collective bargaining rights? | D21: Please Select | E21: ▪ Total number of employees by employment type and contract ▪ Employee retention or turnover rate ▪ Percentage of employees covered by collective bargaining agreements | G21: =VLOOKUP(D21,Refs!$A$1:$B$7,2,FALSE) -> N/A | H21: =IF(ISERROR(G21/4),"N/A",G21/"4") -> N/A
B22: Employee Representation | C22: Do you have clear processes for employee engagement, representation, feedback, and grievance resolution? | D22: Please Select | E22: ▪ Employee engagement processes in place, including surveys, worker councils, and grievance mechanisms. ▪ Proportion of employees covered by formal representation structures ▪ Number of employee grievances reported and categorised by type (e.g., harassment, discrimination) | G22: =VLOOKUP(D22,Refs!$A$1:$B$7,2,FALSE) -> N/A | H22: =IF(ISERROR(G22/4),"N/A",G22/"4") -> N/A
B23: Training and Development | C23: Has your business implemented a training and development policy that ensures all full-time employees have access to training and professional development opportunities? | D23: Please Select | E23: ▪ Information on the company's training and development policy. ▪ Average number of training hours per employee per year. ▪ Percentage of employees receiving regular performance and career development reviews | G23: =VLOOKUP(D23,Refs!$A$1:$B$7,2,FALSE) -> N/A | H23: =IF(ISERROR(G23/4),"N/A",G23/"4") -> N/A
B24: Fair Compensation | C24: Do you ensure pay and benefits are sufficient for employees to cover living costs and maintain a healthy work-life balance? | D24: Please Select | E24: ▪ Ratios of standard entry level wage by gender compared to local minimum wage. ▪ Information on any living wage assessments carried out and measures taken to close any living wage gap. ▪ Number of days of annual paid leave provided for full time employees. | G24: =VLOOKUP(D24,Refs!$A$1:$B$7,2,FALSE) -> N/A | H24: =IF(ISERROR(G24/4),"N/A",G24/"4") -> N/A
B25: Health and Wellbeing | C25: Do you have policies that promote health and well-being, ensure safe working conditions, and provide fair access to parental leave? | D25: Please Select | E25: ▪ Information on measures taken to promote health and wellbeing and ensure safe working conditions ▪ Number of weeks of paid Parental Leave offered to male and female staff ▪ The number and rate of recordable work related injuries and fatalities | G25: =VLOOKUP(D25,Refs!$A$1:$B$7,2,FALSE) -> N/A | H25: =IF(ISERROR(G25/4),"N/A",G25/"4") -> N/A
B26: Diversity and Equality | C26: Do your policies and practices ensure all individuals, regardless of background, identity, or circumstances, have fair opportunities, equal treatment, and a sense of belonging in your workplace? | D26: Please Select | E26: ▪ Diversity of governance bodies and employees ▪ Ratio of basic salary and remuneration of women to men ▪ Information on the company's Diversity, Equity and Inclusion policy | G26: =VLOOKUP(D26,Refs!$A$1:$B$7,2,FALSE) -> N/A | H26: =IF(ISERROR(G26/4),"N/A",G26/"4") -> N/A
B27: Local Communities | C27: Do you engage with local communities to assess and mitigate its impact, and actively contribute to social and economic well-being? | D27: Please Select | E27: ▪ Percentage of the company's expenditure on local suppliers ▪ Percentage of the company's managers hired form the local area ▪ The total value of funds and in-kind assistance provided for community charities or causes. | G27: =VLOOKUP(D27,Refs!$A$1:$B$7,2,FALSE) -> N/A | H27: =IF(ISERROR(G27/4),"N/A",G27/"4") -> N/A
B28: Social Score | D28: =IF(COUNTIF(G21:G27,"<>N/A")=0,"Awaiting Score",SUM(G21:G27)/(COUNTIF(G21:G27,"<>N/A")*4)) -> Awaiting Score
B30: Environmental Dimension
B31: Topic | C31: Question | D31: Response | E31: Reporting Disclosures
B32: Energy | C32: Does your business monitor and report energy usage, implement measures to improve efficiency and conservation, and use 100% renewable energy or have a clear plan to transition? | D32: Please Select | E32: ▪ Total energy consumption within the organisation ▪ Information on energy efficieny meausures implemented ▪ Percentage of energy consumed from renewable sources | G32: =VLOOKUP(D32,Refs!$A$1:$B$7,2,FALSE) -> N/A | H32: =IF(ISERROR(G32/4),"N/A",G32/"4") -> N/A
B33: Emissions | C33: Do you monitor and report your Greenhouse Gas emissions, and do you have a science-based target with a clear plan to achieve Net Zero? | D33: Please Select | E33: ▪ Total Scope 1,2 and 3 Greenhouse Gas Emissions (Co2e) ▪ Information on Net Zero targets and alignment to Science Based Targets ▪ Information on the company's emissions reduction plan | G33: =VLOOKUP(D33,Refs!$A$1:$B$7,2,FALSE) -> N/A | H33: =IF(ISERROR(G33/4),"N/A",G33/"4") -> N/A
B34: Water and Effluents | C34: Do you implement measures to improve water efficiency and conservation, including increasing the use of recycled or recovered water and ensuring where relevant that wastewater management complies with legal and regulatory standards? | D34: Please Select | E34: ▪ Total water withdrawals by source ▪ Information on water efficiency measures implemented by the company. ▪ Total Freshwater and Non-Freshwater discharges | G34: =VLOOKUP(D34,Refs!$A$1:$B$7,2,FALSE) -> N/A | H34: =IF(ISERROR(G34/4),"N/A",G34/"4") -> N/A
B35: Waste | C35: Do you monitor the waste generated by your organisation, have a plan to maximise reduction, reuse, and recycling, and, where applicable, ensure hazardous waste is managed and disposed of responsibly? | D35: Please Select | E35: ▪ Waste generated by material and means of disposal ▪ Information on recovery and recycling programs in place ▪ Hazardous waste generated by material and means of disposal | G35: =VLOOKUP(D35,Refs!$A$1:$B$7,2,FALSE) -> N/A | H35: =IF(ISERROR(G35/4),"N/A",G35/"4") -> N/A
B36: Materials | C36: Does your business monitor and reduce the environmental impact of the materials it uses, including packaging, and, where applicable, have a plan to identify and eliminate potentially harmful chemicals in its products or processes? | D36: Please Select | E36: ▪ Consumable materials used by material type and weight and information on their environmental impacts ▪ Plans to improve the environmental impact of consumable materials used ▪ Information on any chemicals and materials of concern used and plans to elimate them | G36: =VLOOKUP(D36,Refs!$A$1:$B$7,2,FALSE) -> N/A | H36: =IF(ISERROR(G36/4),"N/A",G36/"4") -> N/A
B37: Biodiversity | C37: Do you measure and take steps to reduce your impact on nature and biodiversity, including initiatives to minimise supply chain impacts? | D37: Please Select | E37: ▪ Information on the nature of significant direct and indirect impacts on biodiversity ▪ Initiatives to reduce impacts on biodiversity from the company's operations or suppliers. | G37: =VLOOKUP(D37,Refs!$A$1:$B$7,2,FALSE) -> N/A | H37: =IF(ISERROR(G37/4),"N/A",G37/"4") -> N/A
B38: Environmental Score | D38: =IF(COUNTIF(G32:G37,"<>N/A")=0,"Awaiting Score",SUM(G32:G37)/(COUNTIF(G32:G37,"<>N/A")*4)) -> Awaiting Score

Sheet Report
B2: Sustainable Business Self Assessment
B3: =Instructions!B7 & " Sustainability Scorecard for " &'Self Assessment'!D6 -> Sustainability Scorecard for Example Company
B5: Rating | C5: =IF(C30>=0.8, "Rated A", IF(C30>0.6, "Rated B", IF(C30>0.4, "Rated C", IF(C30>0.2, "Rated D",IF(C30>0, "Satisfactory", "Rated E"))))) -> #DIV/0!
B7: Governance | C7: ='Self Assessment'!D17 -> Awaiting Score
B8: ='Self Assessment'!B10 -> Strategic Alignment | C8: ='Self Assessment'!H10 -> N/A
B9: ='Self Assessment'!B11 -> Integrated Planning | C9: ='Self Assessment'!H11 -> N/A
B10: ='Self Assessment'!B12 -> Reporting and Transparency | C10: ='Self Assessment'!H12 -> N/A
B11: ='Self Assessment'!B13 -> Procurement | C11: ='Self Assessment'!H13 -> N/A
B12: ='Self Assessment'!B14 -> Fraud and Corruption | C12: ='Self Assessment'!H14 -> N/A
B13: ='Self Assessment'!B15 -> Data Privacy | C13: ='Self Assessment'!H15 -> N/A
B14: ='Self Assessment'!B16 -> Modern Slavery | C14: ='Self Assessment'!H16 -> N/A
B15: Social | C15: ='Self Assessment'!D28 -> Awaiting Score
B16: ='Self Assessment'!B21 -> Labour Practices | C16: ='Self Assessment'!H21 -> N/A
B17: ='Self Assessment'!B22 -> Employee Representation | C17: ='Self Assessment'!H22 -> N/A
B18: ='Self Assessment'!B23 -> Training and Development | C18: ='Self Assessment'!H23 -> N/A
B19: ='Self Assessment'!B24 -> Fair Compensation | C19: ='Self Assessment'!H24 -> N/A
B20: ='Self Assessment'!B25 -> Health and Wellbeing | C20: ='Self Assessment'!H25 -> N/A
B21: ='Self Assessment'!B26 -> Diversity and Equality | C21: ='Self Assessment'!H26 -> N/A
B22: ='Self Assessment'!B27 -> Local Communities | C22: ='Self Assessment'!H27 -> N/A
B23: Environment | C23: ='Self Assessment'!D38 -> Awaiting Score
B24: ='Self Assessment'!B32 -> Energy | C24: ='Self Assessment'!H32 -> N/A
B25: ='Self Assessment'!B33 -> Emissions | C25: ='Self Assessment'!H33 -> N/A
B26: ='Self Assessment'!B34 -> Water and Effluents | C26: ='Self Assessment'!H34 -> N/A
B27: ='Self Assessment'!B35 -> Waste | C27: ='Self Assessment'!H35 -> N/A
B28: ='Self Assessment'!B36 -> Materials | C28: ='Self Assessment'!H36 -> N/A
B29: ='Self Assessment'!B37 -> Biodiversity | C29: ='Self Assessment'!H37 -> N/A
B30: Total Score | C30: =SUM('Self Assessment'!G10:G37)/((COUNTIF('Self Assessment'!G10:G16,"<>N/A")*4)+(COUNTIF('Self Assessment'!G21:G27,"<>N/A")*4)+(COUNTIF('Self Assessment'!G32:G37,"<>N/A")*4)) -> #DIV/0!

Sheet Refs
A1: Please Select | B1: N/A | C1: 2024
A2: Fully achieved and working well | B2: 4 | C2: 2025
A3: Mostly achieved but still room to improve | B3: 3 | C3: 2026
A4: Making progress but not yet there | B4: 2 | C4: 2027
A5: Just getting started | B5: 1 | C5: 2028
A6: Not yet started | B6: 0 | C6: 2029
A7: N/A – Not material to our organisation | B7: N/A | C7: 2030
